FeatureFlex/__init__.py
FeatureFlex/comparison.py
FeatureFlex/evaluation.py
FeatureFlex/feature_selector.py
FeatureFlex/main.py
FeatureFlex/model.py
FeatureFlex/model_optimizer.py
FeatureFlex/preprocessing.py
FeatureFlex/test.py
FeatureFlex-0.1.67.dist-info/LICENSE.md
FeatureFlex-0.1.67.dist-info/METADATA
FeatureFlex-0.1.67.dist-info/WHEEL
FeatureFlex-0.1.67.dist-info/entry_points.txt
FeatureFlex-0.1.67.dist-info/top_level.txt
FeatureFlex-0.1.67.dist-info/RECORD
