Metadata-Version: 2.2
Name: FeatureFlex
Version: 0.1.67
Summary: An AutoML project with various machine learning capabilities.
Home-page: https://github.com/SaintAngeLs/CS-MINI-2024Z-AutoML_project_2
Author: SaintAngeLs
Author-email: info@itsharppro.com
Classifier: Programming Language :: Python :: 3
Classifier: License :: OSI Approved :: MIT License
Classifier: Operating System :: OS Independent
Requires-Python: >=3.6
License-File: LICENSE.md
Requires-Dist: alembic==1.14.0
Requires-Dist: autofeat==2.1.3
Requires-Dist: Boruta==0.4.3
Requires-Dist: certifi==2024.12.14
Requires-Dist: charset-normalizer==3.4.1
Requires-Dist: cloudpickle==3.1.0
Requires-Dist: colorlog==6.9.0
Requires-Dist: contourpy==1.3.1
Requires-Dist: cycler==0.12.1
Requires-Dist: filelock==3.16.1
Requires-Dist: flexcache==0.3
Requires-Dist: flexparser==0.4
Requires-Dist: fonttools==4.55.3
Requires-Dist: fsspec==2024.12.0
Requires-Dist: greenlet==3.1.1
Requires-Dist: idna==3.10
Requires-Dist: imbalanced-learn==0.13.0
Requires-Dist: imblearn==0.0
Requires-Dist: Jinja2==3.1.5
Requires-Dist: joblib==1.4.2
Requires-Dist: kagglehub==0.3.6
Requires-Dist: kiwisolver==1.4.8
Requires-Dist: lightgbm==4.5.0
Requires-Dist: llvmlite==0.43.0
Requires-Dist: Mako==1.3.8
Requires-Dist: MarkupSafe==3.0.2
Requires-Dist: matplotlib==3.10.0
Requires-Dist: mpmath==1.3.0
Requires-Dist: networkx==3.4.2
Requires-Dist: numba==0.60.0
Requires-Dist: numpy==1.26.4
Requires-Dist: nvidia-cublas-cu12==12.4.5.8
Requires-Dist: nvidia-cuda-cupti-cu12==12.4.127
Requires-Dist: nvidia-cuda-nvrtc-cu12==12.4.127
Requires-Dist: nvidia-cuda-runtime-cu12==12.4.127
Requires-Dist: nvidia-cudnn-cu12==9.1.0.70
Requires-Dist: nvidia-cufft-cu12==11.2.1.3
Requires-Dist: nvidia-curand-cu12==10.3.5.147
Requires-Dist: nvidia-cusolver-cu12==11.6.1.9
Requires-Dist: nvidia-cusparse-cu12==12.3.1.170
Requires-Dist: nvidia-nccl-cu12==2.21.5
Requires-Dist: nvidia-nvjitlink-cu12==12.4.127
Requires-Dist: nvidia-nvtx-cu12==12.4.127
Requires-Dist: optuna==4.1.0
Requires-Dist: packaging==24.2
Requires-Dist: pandas==2.2.3
Requires-Dist: pdfkit==1.0.0
Requires-Dist: pillow==11.0.0
Requires-Dist: Pint==0.24.4
Requires-Dist: platformdirs==4.3.6
Requires-Dist: pyparsing==3.2.1
Requires-Dist: python-dateutil==2.9.0.post0
Requires-Dist: pytz==2024.2
Requires-Dist: PyYAML==6.0.2
Requires-Dist: requests==2.32.3
Requires-Dist: scikit-learn==1.5.0
Requires-Dist: scipy==1.14.1
Requires-Dist: setuptools==75.6.0
Requires-Dist: shap==0.46.0
Requires-Dist: six==1.17.0
Requires-Dist: sklearn-compat==0.1.3
Requires-Dist: slicer==0.0.8
Requires-Dist: SQLAlchemy==2.0.36
Requires-Dist: sympy==1.13.1
Requires-Dist: threadpoolctl==3.5.0
Requires-Dist: torch==2.5.1
Requires-Dist: tqdm==4.67.1
Requires-Dist: triton==3.1.0
Requires-Dist: typing_extensions==4.12.2
Requires-Dist: tzdata==2024.2
Requires-Dist: urllib3==2.3.0
Requires-Dist: xgboost==2.1.3
Dynamic: author
Dynamic: author-email
Dynamic: classifier
Dynamic: description
Dynamic: description-content-type
Dynamic: home-page
Dynamic: requires-dist
Dynamic: requires-python
Dynamic: summary
